show_file_tree-0.0.1.dist-info/licenses/LICENSE.md
showfilestree/__init__.py
showfilestree/__main__.py
showfilestree/_version.py
showfilestree/cli.py
showfilestree/gitignore_parser.py
showfilestree/include_exclude.py
showfilestree/md_exporter.py
showfilestree/metadata.py
showfilestree/notes_manager.py
showfilestree/options.py
showfilestree/size_utils.py
showfilestree/sort_utils.py
showfilestree/theme_styles.py
showfilestree/time_filters.py
showfilestree/tree_builder.py
showfilestree/tree_renderer.py
showfilestree/utils.py
show_file_tree-0.0.1.dist-info/METADATA
show_file_tree-0.0.1.dist-info/WHEEL
show_file_tree-0.0.1.dist-info/entry_points.txt
show_file_tree-0.0.1.dist-info/top_level.txt
show_file_tree-0.0.1.dist-info/RECORD
