Metadata-Version: 2.4
Name: show-file-tree
Version: 0.0.1
Summary: A small, fast CLI tool to display styled file/folder trees with rich options.
Author: Rudra Prasad Bhuyan
Project-URL: Homepage, https://github.com/Rudra-G-23/show-file-tree
Project-URL: Bug Tracker, https://github.com/Rudra-G-23/show-file-tree/issues
Keywords: cli,tree,file,directory,rich,typer
Classifier: Development Status :: 3 - Alpha
Classifier: Intended Audience :: Developers
Classifier: License :: OSI Approved :: MIT License
Classifier: Programming Language :: Python :: 3
Classifier: Programming Language :: Python :: 3.8
Classifier: Programming Language :: Python :: 3.9
Classifier: Programming Language :: Python :: 3.10
Classifier: Programming Language :: Python :: 3.11
Classifier: Operating System :: OS Independent
Classifier: Topic :: Software Development :: Libraries :: Python Modules
Classifier: Topic :: System :: Filesystems
Classifier: Topic :: Terminals
Requires-Python: >=3.8
License-File: LICENSE.md
Requires-Dist: rich>=13.0.0
Requires-Dist: typer[all]>=0.9.0
Requires-Dist: pathspec>=0.11.0
Dynamic: license-file
